LICENSE
MANIFEST.in
README.rst
setup.py
django_report_tools.egg-info/PKG-INFO
django_report_tools.egg-info/SOURCES.txt
django_report_tools.egg-info/dependency_links.txt
django_report_tools.egg-info/top_level.txt
report_tools/__init__.py
report_tools/api.py
report_tools/chart_data.py
report_tools/charts.py
report_tools/models.py
report_tools/reports.py
report_tools/urls.py
report_tools/views.py
report_tools/renderers/__init__.py
report_tools/renderers/googlecharts/__init__.py
report_tools/renderers/googlecharts/gviz_api/COPYRIGHT
report_tools/renderers/googlecharts/gviz_api/README
report_tools/renderers/googlecharts/gviz_api/__init__.py
report_tools/renderers/googlecharts/gviz_api/gviz_api.py
report_tools/renderers/googlecharts/gviz_api/gviz_api_test.py
report_tools/templates/report_tools/renderers/googlecharts/barchart.html
report_tools/templates/report_tools/renderers/googlecharts/chart.html
report_tools/templates/report_tools/renderers/googlecharts/columnchart.html
report_tools/templates/report_tools/renderers/googlecharts/linechart.html
report_tools/templates/report_tools/renderers/googlecharts/piechart.html
report_tools/tests/__init__.py
report_tools/tests/reports.py
report_tools/tests/test_all.py
report_tools/tests/views.py
tests/__init__.py
tests/__init__.pyc
tests/manage.py
tests/requirements.txt
tests/runtests.py
tests/runtests.pyc
tests/runtests.sh