Metadata-Version: 1.1
Name: django-report-tools
Version: 0.2.2
Summary: Class-based reports for elegant data views.
Home-page: http://github.com/evanbrumley/django-report-tools
Author: Evan Brumley
Author-email: evan.brumley@gmail.com
License: UNKNOWN
Platform: UNKNOWN
Classifier: Development Status :: 4 - Beta
Classifier: Environment :: Web Environment
Classifier: Framework :: Django
Classifier: Intended Audience :: Developers
Classifier: License :: OSI Approved :: BSD License
Classifier: Operating System :: OS Independent
Classifier: Programming Language :: Python
Classifier: Topic :: Utilities
